LICENSE
MANIFEST.in
README.md
setup.py
labelatory/__init__.py
labelatory/__main__.py
labelatory/connector.py
labelatory/label.py
labelatory/labelatory.py
labelatory/services.py
labelatory.egg-info/PKG-INFO
labelatory.egg-info/SOURCES.txt
labelatory.egg-info/dependency_links.txt
labelatory.egg-info/entry_points.txt
labelatory.egg-info/not-zip-safe
labelatory.egg-info/requires.txt
labelatory.egg-info/top_level.txt
labelatory/templates/add_label.html
labelatory/templates/add_repo.html
labelatory/templates/check_labels.html
labelatory/templates/edit_label.html
labelatory/templates/index.html
labelatory/templates/layout.html