Metadata-Version: 2.1
Name: labelatory
Version: 0.1
Summary: Labelatory - the powerful and the greatest tool         for label management across repositories on different git systems.
Home-page: https://github.com/fedotovdanil570/labelatory
Author: Daniil Fedotov
Author-email: fedotovdanil570@gmail.com
License: UNKNOWN
Keywords: git,github,gitlab,label,labels,repository,api
Platform: UNKNOWN
Classifier: Programming Language :: Python :: 3
Classifier: License :: OSI Approved :: MIT License
Classifier: Operating System :: OS Independent
Classifier: Environment :: Web Environment
Classifier: Framework :: Flask
Classifier: Programming Language :: Python :: Implementation
Classifier: Programming Language :: Python :: 3.6
Classifier: Programming Language :: Python :: 3.7
Classifier: Programming Language :: Python :: 3.8
Classifier: Programming Language :: Python :: 3.9
Classifier: Topic :: Software Development
